sica/__init__.py
sica/_whitening.py
sica/base.py
sica/mutualknn.py
tests/__init__.py
tests/test_StabilizedICA.py
stabilized_ica-2.0.0.dist-info/LICENSE
stabilized_ica-2.0.0.dist-info/METADATA
stabilized_ica-2.0.0.dist-info/WHEEL
stabilized_ica-2.0.0.dist-info/top_level.txt
stabilized_ica-2.0.0.dist-info/RECORD
