Metadata-Version: 2.1
Name: stabilized-ica
Version: 2.0.0
Summary: Stabilized ICA algorithm
Home-page: https://github.com/ncaptier/stabilized-ica
Author: Nicolas Captier
Author-email: nicolas.captier@curie.fr
Classifier: Programming Language :: Python :: 3
Classifier: License :: OSI Approved :: MIT License
Classifier: Operating System :: OS Independent
Requires-Python: >=3.8
License-File: LICENSE
Requires-Dist: matplotlib
Requires-Dist: numpy
Requires-Dist: scipy
Requires-Dist: joblib (>=1.1.0)
Requires-Dist: networkx (>=2.7.1)
Requires-Dist: pandas (>=1.4.2)
Requires-Dist: python-picard (>=0.7)
Requires-Dist: scikit-learn (>=1.0.2)
Requires-Dist: tqdm (>=4.64.0)
Requires-Dist: umap-learn (>=0.5.3)
Provides-Extra: dev
Requires-Dist: pytest ; extra == 'dev'
Provides-Extra: docs
Requires-Dist: sphinx (==5.0.2) ; extra == 'docs'
Requires-Dist: sphinx-gallery (==0.10.0) ; extra == 'docs'
Requires-Dist: numpydoc (==1.2) ; extra == 'docs'
Requires-Dist: nbsphinx (==0.8.9) ; extra == 'docs'
